[{"place_id": 205260452, "licence": "Data \u00a9 OpenStreetMap contributors, ODbL 1.0. http://osm.org/copyright", "osm_type": "way", "osm_id": 816075688, "lat": "37.4803830", "lon": "126.9942574", "class": "highway", "type": "secondary", "place_rank": 26, "importance": 0.05340631342030972, "addresstype": "road", "name": "Hyoryeong-ro", "display_name": "Hyoryeong-ro, Bangbae 1(il)-dong, Seocho-gu, Seoul, 06696, South Korea", "boundingbox": ["37.4801800", "37.4805775", "126.9936400", "126.9948776"]}]