[{"place_id": 205282286, "licence": "Data \u00a9 OpenStreetMap contributors, ODbL 1.0. http://osm.org/copyright", "osm_type": "way", "osm_id": 156298107, "lat": "37.4774545", "lon": "126.9833105", "class": "highway", "type": "residential", "place_rank": 26, "importance": 0.05340631342030972, "addresstype": "road", "name": "Bangbaecheon-ro", "display_name": "Bangbaecheon-ro, Bangbae 2(i)-dong, Seocho-gu, Seoul, 06693, South Korea", "boundingbox": ["37.4773717", "37.4775359", "126.9827839", "126.9838369"]}]