[{"place_id": 206640145, "licence": "Data \u00a9 OpenStreetMap contributors, ODbL 1.0. http://osm.org/copyright", "osm_type": "way", "osm_id": 469944599, "lat": "37.4872545", "lon": "126.9851293", "class": "amenity", "type": "place_of_worship", "place_rank": 30, "importance": 7.29800869763793e-05, "addresstype": "amenity", "name": "Logos church", "display_name": "Logos church, 126, Bangbaecheon-ro, Bangbaebon-dong, Seocho-gu, Seoul, 06568, South Korea", "boundingbox": ["37.4867036", "37.4874952", "126.9847013", "126.9853118"]}]