[{"place_id": 206809941, "licence": "Data \u00a9 OpenStreetMap contributors, ODbL 1.0. http://osm.org/copyright", "osm_type": "way", "osm_id": 230073206, "lat": "37.4899101", "lon": "127.0094679", "class": "highway", "type": "residential", "place_rank": 26, "importance": 0.05340631342030972, "addresstype": "road", "name": "Seocho-daero 42-gil", "display_name": "Seocho-daero 42-gil, Seocho 3(sam)-dong, Seocho-gu, Seoul, 06648, South Korea", "boundingbox": ["37.4877455", "37.4920673", "127.0084147", "127.0105055"]}]