[{"place_id": 402441812, "licence": "Data \u00a9 OpenStreetMap contributors, ODbL 1.0. http://osm.org/copyright", "osm_type": "way", "osm_id": 282429544, "lat": "37.4711564", "lon": "127.0453662", "class": "highway", "type": "residential", "place_rank": 26, "importance": 0.05340631342030972, "addresstype": "road", "name": "Dongsan-ro 12-gil", "display_name": "Dongsan-ro 12-gil, Yangjae 2(i)-dong, Seocho-gu, Seoul, 06784, South Korea", "boundingbox": ["37.4708469", "37.4717244", "127.0450871", "127.0458780"]}]